<_>
   <form_key>kXSce6KacX6WhKA7</form_key>
   <name>Ced_LayBuy</name>
   <channel>community</channel>
   <version_ids>
      <version_ids>2</version_ids>
   </version_ids>
   <summary>Magento LayBuy Payment Gateway Module Developed By Lay-Buy Financial Solutions Pty Ltd (warrin@lay-buys.com)</summary>
   <description>Welcome to Lay-Buys, the leading provider of deferred payment plan solutions for online PayPal merchants globally.

We integrate affordable, flexible, secure, and scalable deferred payment plan solutions into your website shopping cart check-out zone.

Our sophisticated flagship SDK is PUT IT ON LAY-BUY and is powered by PayPal.

PUT IT ON LAY-BUY enables online shoppers to pay-off a product or service via a down payment and up to 3 monthly instalment payments.

Merchants however only deliver the product or service after receipt of the final instalment payment.

This effectively increases sales and radically improves cash flow where all the customer monies are paid directly into your PayPal account.</description>
   <license>Open Software License (OSL)</license>
   <license_uri>http://opensource.org/licenses/osl-3.0.php</license_uri>
   <version>2.1.9.3</version>
   <stability>stable</stability>
   <notes>1. New secure communication protocal.</notes>
   <authors>
      <name>
         <name>Warrin</name>
         <name>Asheesh Singh</name>
         <name>Sanjeev Kumar Gupta</name>
      </name>
      <user>
         <user>warrin</user>
         <user>asheeshsingh</user>
         <user>sanjeevgupta</user>
      </user>
      <email>
         <email>warrin@lay-buys.com</email>
         <email>asheeshsingh@cedcoss.com</email>
         <email>sanjeevkumargupta@cedcoss.com</email>
      </email>
   </authors>
   <depends_php_min>5.1.0</depends_php_min>
   <depends_php_max>6.0.0</depends_php_max>
   <depends>
      <package>
         <name>
            <name/>
         </name>
         <channel>
            <channel/>
         </channel>
         <min>
            <min/>
         </min>
         <max>
            <max/>
         </max>
         <files>
            <files>        </files>
         </files>
      </package>
      <extension>
         <name>
            <name>Core</name>
         </name>
         <min>
            <min/>
         </min>
         <max>
            <max/>
         </max>
      </extension>
   </depends>
   <contents>
      <target>
         <target>magelocal</target>
         <target>magelocal</target>
         <target>magedesign</target>
         <target>magedesign</target>
         <target>mageetc</target>
         <target>magelocale</target>
         <target>mageskin</target>
         <target>mageskin</target>
         <target>mage</target>
         <target>magedesign</target>
         <target>magedesign</target>
      </target>
      <path>
         <path/>
         <path>Ced/LayBuy/</path>
         <path>frontend/base/default/layout/laybuy.xml</path>
         <path>frontend/base/default/template/laybuy/</path>
         <path>modules/Ced_LayBuy.xml</path>
         <path>en_US/Ced_LayBuy.csv</path>
         <path>frontend/base/default/css/laybuy/</path>
         <path>frontend/base/default/images/laybuy/</path>
         <path>js/laybuy/</path>
         <path>adminhtml/default/default/layout/laybuy.xml</path>
         <path>adminhtml/default/default/template/laybuy/</path>
      </path>
      <type>
         <type>file</type>
         <type>dir</type>
         <type>file</type>
         <type>dir</type>
         <type>file</type>
         <type>file</type>
         <type>dir</type>
         <type>dir</type>
         <type>dir</type>
         <type>file</type>
         <type>dir</type>
      </type>
      <include>
         <include/>
         <include/>
         <include/>
         <include/>
         <include/>
         <include/>
         <include/>
         <include/>
         <include/>
         <include/>
         <include/>
      </include>
      <ignore>
         <ignore/>
         <ignore/>
         <ignore/>
         <ignore/>
         <ignore/>
         <ignore/>
         <ignore/>
         <ignore/>
         <ignore/>
         <ignore/>
         <ignore/>
      </ignore>
   </contents>
</_>
